opensquirrel/__init__.py
opensquirrel/circuit.py
opensquirrel/circuit_builder.py
opensquirrel/circuit_matrix_calculator.py
opensquirrel/common.py
opensquirrel/default_gate_modifiers.py
opensquirrel/default_instructions.py
opensquirrel/exceptions.py
opensquirrel/register_manager.py
opensquirrel/ir/__init__.py
opensquirrel/ir/control_instruction.py
opensquirrel/ir/expression.py
opensquirrel/ir/ir.py
opensquirrel/ir/non_unitary.py
opensquirrel/ir/single_qubit_gate.py
opensquirrel/ir/statement.py
opensquirrel/ir/two_qubit_gate.py
opensquirrel/ir/unitary.py
opensquirrel/ir/default_gates/__init__.py
opensquirrel/ir/default_gates/single_qubit_gates.py
opensquirrel/ir/default_gates/two_qubit_gates.py
opensquirrel/ir/semantics/__init__.py
opensquirrel/ir/semantics/bsr.py
opensquirrel/ir/semantics/canonical_gate.py
opensquirrel/ir/semantics/controlled_gate.py
opensquirrel/ir/semantics/gate_semantic.py
opensquirrel/ir/semantics/matrix_gate.py
opensquirrel/passes/__init__.py
opensquirrel/passes/decomposer/__init__.py
opensquirrel/passes/decomposer/aba_decomposer.py
opensquirrel/passes/decomposer/cnot2cz_decomposer.py
opensquirrel/passes/decomposer/cnot_decomposer.py
opensquirrel/passes/decomposer/cz_decomposer.py
opensquirrel/passes/decomposer/general_decomposer.py
opensquirrel/passes/decomposer/mckay_decomposer.py
opensquirrel/passes/decomposer/swap2cnot_decomposer.py
opensquirrel/passes/decomposer/swap2cz_decomposer.py
opensquirrel/passes/exporter/__init__.py
opensquirrel/passes/exporter/general_exporter.py
opensquirrel/passes/exporter/quantify_scheduler_exporter.py
opensquirrel/passes/exporter/cqasmv1_exporter/__init__.py
opensquirrel/passes/exporter/cqasmv1_exporter/cqasmv1_exporter.py
opensquirrel/passes/mapper/__init__.py
opensquirrel/passes/mapper/check_mapper.py
opensquirrel/passes/mapper/general_mapper.py
opensquirrel/passes/mapper/mapping.py
opensquirrel/passes/mapper/mip_mapper.py
opensquirrel/passes/mapper/qgym_mapper.py
opensquirrel/passes/mapper/qubit_remapper.py
opensquirrel-0.9.0.dist-info/METADATA
opensquirrel-0.9.0.dist-info/WHEEL
opensquirrel-0.9.0.dist-info/licenses/LICENSE.md
opensquirrel-0.9.0.dist-info/RECORD
