Metadata-Version: 2.4
Name: opensquirrel
Version: 0.9.0
Summary: A quantum circuit transformation and manipulation tool
Project-URL: Homepage, https://qutech-delft.github.io/OpenSquirrel/
Project-URL: Repository, https://github.com/QuTech-Delft/OpenSquirrel
Author-email: Quantum Inspire <support@quantum-inspire.com>
License-Expression: Apache-2.0
License-File: LICENSE.md
Keywords: circuits,compilation,quantum
Classifier: Development Status :: 3 - Alpha
Classifier: License :: OSI Approved :: Apache Software License
Classifier: Programming Language :: Python :: 3
Classifier: Programming Language :: Python :: 3.10
Classifier: Programming Language :: Python :: 3.11
Classifier: Programming Language :: Python :: 3.12
Classifier: Programming Language :: Python :: 3.13
Requires-Python: >=3.10.0
Requires-Dist: libqasm==1.2.1
Requires-Dist: networkx>=3.4.2
Requires-Dist: numpy>=2.2.6
Requires-Dist: scipy>=1.15.3
